xmppy/Messenger.py
xmppy/__init__.py
xmppy/gpg_holder.py
xmppy-0.11.dist-info/LICENSE
xmppy-0.11.dist-info/METADATA
xmppy-0.11.dist-info/WHEEL
xmppy-0.11.dist-info/entry_points.txt
xmppy-0.11.dist-info/top_level.txt
xmppy-0.11.dist-info/RECORD
