Metadata-Version: 2.1
Name: xmppy
Version: 0.11
Summary: Python module for receiving and sending massage using XMPP protocol
Home-page: UNKNOWN
Author: Albert Szadziński
Author-email: albert.szadzinski@smcebi.edu.pl
License: MIT
Platform: UNKNOWN
Requires-Dist: sleekxmpp
Requires-Dist: python-gnupg
Requires-Dist: dnspython
